{
  "generatedAt": "2026-06-12T22:42:39.016Z",
  "reportPath": "docs/reports/results/backtest-2026-06-12T22-42-22-260Z.json",
  "qualityGateStatus": "PASS",
  "reliabilityScore": 98,
  "horizonConfidence": {
    "14d": {
      "powerlawError": 0.053012917440583784,
      "naiveError": 0.05478665273327779,
      "status": "beats-naive"
    },
    "30d": {
      "powerlawError": 0.08298569588394204,
      "naiveError": 0.08669731140138434,
      "status": "beats-naive"
    },
    "60d": {
      "powerlawError": 0.13965334679762115,
      "naiveError": 0.14222123729788122,
      "status": "beats-naive"
    },
    "90d": {
      "powerlawError": 0.15554570130543682,
      "naiveError": 0.18897599783635985,
      "status": "beats-naive"
    }
  },
  "ensembleEnabled": false,
  "ensembleReason": "Regime signals are context-only until ablation beats the calibrated power-law baseline out of sample."
}
